chromecast_volumecontrol/__init__.py
chromecast_volumecontrol/control_chromecasts.py
chromecast_volumecontrol/flask_endpoint.py
chromecast_volumecontrol/gui.py
chromecast_volumecontrol_merklel-0.0.1.dist-info/LICENSE
chromecast_volumecontrol_merklel-0.0.1.dist-info/METADATA
chromecast_volumecontrol_merklel-0.0.1.dist-info/WHEEL
chromecast_volumecontrol_merklel-0.0.1.dist-info/top_level.txt
chromecast_volumecontrol_merklel-0.0.1.dist-info/RECORD
